vsar/__init__.py
vsar/version.py
vsar/cli/__init__.py
vsar/cli/formatters.py
vsar/cli/main.py
vsar/encoding/__init__.py
vsar/encoding/base.py
vsar/encoding/roles.py
vsar/encoding/vsa_encoder.py
vsar/ide/__init__.py
vsar/ide/highlighter.py
vsar/ide/main.py
vsar/ide/runner.py
vsar/kb/__init__.py
vsar/kb/persistence.py
vsar/kb/store.py
vsar/kernel/__init__.py
vsar/kernel/base.py
vsar/kernel/models.py
vsar/kernel/types.py
vsar/kernel/vsa_backend.py
vsar/language/__init__.py
vsar/language/ast.py
vsar/language/grammar.lark
vsar/language/loader.py
vsar/language/parser.py
vsar/retrieval/__init__.py
vsar/retrieval/cleanup.py
vsar/retrieval/query.py
vsar/retrieval/unbind.py
vsar/semantics/__init__.py
vsar/semantics/chaining.py
vsar/semantics/engine.py
vsar/semantics/join.py
vsar/semantics/substitution.py
vsar/symbols/__init__.py
vsar/symbols/basis.py
vsar/symbols/registry.py
vsar/symbols/spaces.py
vsar/trace/__init__.py
vsar/trace/collector.py
vsar/trace/events.py
vsar/utils/__init__.py
vsar-0.4.0.dist-info/METADATA
vsar-0.4.0.dist-info/WHEEL
vsar-0.4.0.dist-info/entry_points.txt
vsar-0.4.0.dist-info/top_level.txt
vsar-0.4.0.dist-info/RECORD
