Metadata-Version: 2.4
Name: vsar
Version: 0.4.0
Summary: VSAR: VSA-grounded reasoning with approximate joins
Author: VSAR Contributors
License: MIT
Keywords: vsa,hyperdimensional-computing,reasoning,knowledge-graphs
Classifier: Development Status :: 3 - Alpha
Classifier: Intended Audience :: Science/Research
Classifier: Programming Language :: Python :: 3.11
Classifier: Programming Language :: Python :: 3.12
Requires-Python: >=3.11
Requires-Dist: h5py>=3.15.1
Requires-Dist: jax>=0.8.2
Requires-Dist: jaxlib>=0.8.2
Requires-Dist: lark>=1.3.1
Requires-Dist: numpy>=2.4.0
Requires-Dist: pydantic>=2.12.5
Requires-Dist: typer>=0.21.0
Requires-Dist: vsax>=1.3.0
Provides-Extra: dev
Provides-Extra: docs
